Workbook

Sheet Executive Dashboard
A1: EXECUTIVE DASHBOARD — RETAIL SALES FY2024
A2: Fictional Retail Co. | Business Analysis Case Study | Prepared by: Aira M. Mapute
A4: TOTAL REVENUE | C4: GROSS PROFIT | E4: OVERALL GP% | G4: TOTAL UNITS | I4: NET REVENUE
A5: ='Monthly Summary'!B17 -> 11314544 | C5: ='Monthly Summary'!D17 -> 5932281.4 | E5: ='Monthly Summary'!E17 -> 0.52430584 | G5: ='Monthly Summary'!G17 -> 83685 | I5: ='Monthly Summary'!F17 -> 10827184
A8: TOP REGIONS BY REVENUE | F8: TOP CATEGORIES BY REVENUE
A9: Region | B9: Revenue | C9: GP Margin | D9: Units | E9: Share | F9: Category | G9: Revenue | H9: GP Margin | I9: Units | J9: Avg Price
A10: ='Regional Analysis'!A5 -> East | B10: ='Regional Analysis'!B5 -> 2561299.7 | C10: ='Regional Analysis'!E5 -> 0.5249027 | D10: ='Regional Analysis'!F5 -> 18473 | E10: ='Regional Analysis'!G5 -> 0.22637233 | F10: ='Category Analysis'!A5 -> Groceries | G10: ='Category Analysis'!B5 -> 2463240 | H10: ='Category Analysis'!E5 -> 0.51445192 | I10: ='Category Analysis'!F5 -> 16997 | J10: ='Category Analysis'!G5 -> 143.5
A11: ='Regional Analysis'!A6 -> Central | B11: ='Regional Analysis'!B6 -> 2337199.8 | C11: ='Regional Analysis'!E6 -> 0.53149332 | D11: ='Regional Analysis'!F6 -> 16171 | E11: ='Regional Analysis'!G6 -> 0.20656598 | F11: ='Category Analysis'!A6 -> Apparel | G11: ='Category Analysis'!B6 -> 2392165.7 | H11: ='Category Analysis'!E6 -> 0.52432019 | I11: ='Category Analysis'!F6 -> 16550 | J11: ='Category Analysis'!G6 -> 141.9
A12: ='Regional Analysis'!A7 -> South | B12: ='Regional Analysis'!B7 -> 2189845.9 | C12: ='Regional Analysis'!E7 -> 0.52003353 | D12: ='Regional Analysis'!F7 -> 15920 | E12: ='Regional Analysis'!G7 -> 0.19354257 | F12: ='Category Analysis'!A7 -> Furniture | G12: ='Category Analysis'!B7 -> 2295371 | H12: ='Category Analysis'!E7 -> 0.54075488 | I12: ='Category Analysis'!F7 -> 16588 | J12: ='Category Analysis'!G7 -> 138.52
A13: ='Regional Analysis'!A8 -> North | B13: ='Regional Analysis'!B8 -> 2170520.5 | C13: ='Regional Analysis'!E8 -> 0.52005891 | D13: ='Regional Analysis'!F8 -> 17241 | E13: ='Regional Analysis'!G8 -> 0.19183456 | F13: ='Category Analysis'!A8 -> Electronics | G13: ='Category Analysis'!B8 -> 2143624.1 | H13: ='Category Analysis'!E8 -> 0.51735481 | I13: ='Category Analysis'!F8 -> 16599 | J13: ='Category Analysis'!G8 -> 130.37
A14: ='Regional Analysis'!A9 -> West | B14: ='Regional Analysis'!B9 -> 2055677.9 | C14: ='Regional Analysis'!E9 -> 0.52442574 | D14: ='Regional Analysis'!F9 -> 15880 | E14: ='Regional Analysis'!G9 -> 0.18168455 | F14: ='Category Analysis'!A9 -> Sports | G14: ='Category Analysis'!B9 -> 2020143 | H14: ='Category Analysis'!E9 -> 0.52498995 | I14: ='Category Analysis'!F9 -> 16951 | J14: ='Category Analysis'!G9 -> 118.58

Sheet Raw Data
A1: Month | B1: Region | C1: Category | D1: Units_Sold | E1: Unit_Price | F1: Revenue | G1: COGS | H1: Gross_Profit | I1: Returns | J1: Net_Revenue
A2: Jan | B2: North | C2: Electronics | D2: 377 | E2: 36.72 | F2: 13843.44 | G2: 7411.61 | H2: 6431.83 | I2: 375.74 | J2: 13467.7
A3: Jan | B3: North | C3: Apparel | D3: 121 | E3: 186.75 | F3: 22596.75 | G3: 11731.66 | H3: 10865.09 | I3: 1637.19 | J3: 20959.56
A4: Jan | B4: North | C4: Furniture | D4: 94 | E4: 151.72 | F4: 14261.68 | G4: 5104.91 | H4: 9156.77 | I4: 236.15 | J4: 14025.53
A5: Jan | B5: North | C5: Groceries | D5: 169 | E5: 131.29 | F5: 22188.01 | G5: 7913 | H5: 14275.01 | I5: 530.71 | J5: 21657.3
A6: Jan | B6: North | C6: Sports | D6: 382 | E6: 178.32 | F6: 68118.24 | G6: 30985.62 | H6: 37132.62 | I6: 2823.14 | J6: 65295.1
A7: Jan | B7: South | C7: Electronics | D7: 192 | E7: 204.26 | F7: 39217.92 | G7: 13789.99 | H7: 25427.93 | I7: 2604.36 | J7: 36613.56
A8: Jan | B8: South | C8: Apparel | D8: 407 | E8: 111.43 | F8: 45352.01 | G8: 19023.71 | H8: 26328.3 | I8: 1137.06 | J8: 44214.95
A9: Jan | B9: South | C9: Furniture | D9: 440 | E9: 90.78 | F9: 39943.2 | G9: 14906.26 | H9: 25036.94 | I9: 669.85 | J9: 39273.35
A10: Jan | B10: South | C10: Groceries | D10: 483 | E10: 92.55 | F10: 44701.65 | G10: 18601.71 | H10: 26099.94 | I10: 582.98 | J10: 44118.67
A11: Jan | B11: South | C11: Sports | D11: 285 | E11: 138.69 | F11: 39526.65 | G11: 23450.33 | H11: 16076.32 | I11: 1442.62 | J11: 38084.03
A12: Jan | B12: East | C12: Electronics | D12: 332 | E12: 80.36 | F12: 26679.52 | G12: 13530.78 | H12: 13148.74 | I12: 1920.44 | J12: 24759.08
A13: Jan | B13: East | C13: Apparel | D13: 235 | E13: 148.56 | F13: 34911.6 | G13: 18368.49 | H13: 16543.11 | I13: 461.1 | J13: 34450.5
... A301: Dec | B301: Central | C301: Sports | D301: 349 | E301: 141.61 | F301: 49421.89 | G301: 21315.48 | H301: 28106.41 | I301: 3935.17 | J301: 45486.72

Sheet Monthly Summary
A1: RETAIL SALES — MONTHLY PERFORMANCE SUMMARY
A2: FY 2024 | Fictional Retail Co. | BA Portfolio Case Study
A4: Month | B4: Total Revenue | C4: Total COGS | D4: Gross Profit | E4: GP Margin % | F4: Net Revenue | G4: Units Sold | H4: Avg Unit Price
A5: Jan | B5: 800769.48 | C5: 380672.81 | D5: 420096.67 | E5: =D5/B5 -> 0.52461624 | F5: 766503.19 | G5: 7195 | H5: 126.68
A6: Feb | B6: 908436 | C6: 436804.85 | D6: 471631.15 | E6: =D6/B6 -> 0.51916827 | F6: 868320.7 | G6: 6937 | H6: 128.53
A7: Mar | B7: 955503.72 | C7: 438808.03 | D7: 516695.69 | E7: =D7/B7 -> 0.54075738 | F7: 912966.57 | G7: 6714 | H7: 136.76
A8: Apr | B8: 577555.56 | C8: 276651.23 | D8: 300904.33 | E8: =D8/B8 -> 0.52099633 | F8: 549597.81 | G8: 5744 | H8: 105.32
A9: May | B9: 862082.59 | C9: 441552.55 | D9: 420530.04 | E9: =D9/B9 -> 0.48780714 | F9: 827930.5 | G9: 6331 | H9: 131.91
A10: Jun | B10: 1041230.5 | C10: 497651.23 | D10: 543579.25 | E10: =D10/B10 -> 0.52205468 | F10: 1001178 | G10: 7700 | H10: 133.37
A11: Jul | B11: 935454.43 | C11: 446481.84 | D11: 488972.59 | E11: =D11/B11 -> 0.52271129 | F11: 894083.48 | G11: 6854 | H11: 133.08
A12: Aug | B12: 954117.12 | C12: 431891.07 | D12: 522226.05 | E12: =D12/B12 -> 0.54733957 | F12: 914018.32 | G12: 6561 | H12: 145.98
A13: Sep | B13: 1153530.8 | C13: 555777.34 | D13: 597753.43 | E13: =D13/B13 -> 0.51819461 | F13: 1098942.3 | G13: 7042 | H13: 163.17
A14: Oct | B14: 1098405.7 | C14: 509421.45 | D14: 588984.25 | E14: =D14/B14 -> 0.5362174 | F14: 1054994.2 | G14: 7600 | H14: 147.8
A15: Nov | B15: 1209263.5 | C15: 579740.54 | D15: 629522.96 | E15: =D15/B15 -> 0.52058378 | F15: 1152223.5 | G15: 7876 | H15: 154.53
A16: Dec | B16: 818194.47 | C16: 386809.46 | D16: 431385.01 | E16: =D16/B16 -> 0.52724019 | F16: 786425.02 | G16: 7131 | H16: 107.74
A17: TOTAL | B17: =SUM(B5:B16) -> 11314544 | C17: =SUM(C5:C16) -> 5382262.4 | D17: =SUM(D5:D16) -> 5932281.4 | E17: =D17/B17 -> 0.52430584 | F17: =SUM(F5:F16) -> 10827184 | G17: =SUM(G5:G16) -> 83685 | H17: =AVERAGE(H5:H16) -> 134.5725

Sheet Regional Analysis
A1: REGIONAL PERFORMANCE ANALYSIS
A2: Revenue, Margin & Growth by Region
A4: Region | B4: Total Revenue | C4: Total COGS | D4: Gross Profit | E4: GP Margin % | F4: Total Units | G4: Revenue Share %
A5: East | B5: 2561299.7 | C5: 1216866.6 | D5: 1344433.1 | E5: =D5/B5 -> 0.5249027 | F5: 18473 | G5: =B5/11314544 -> 0.22637233
A6: Central | B6: 2337199.8 | C6: 1094993.7 | D6: 1242206.1 | E6: =D6/B6 -> 0.53149332 | F6: 16171 | G6: =B6/11314544 -> 0.20656598
A7: South | B7: 2189845.9 | C7: 1051052.6 | D7: 1138793.3 | E7: =D7/B7 -> 0.52003353 | F7: 15920 | G7: =B7/11314544 -> 0.19354257
A8: North | B8: 2170520.5 | C8: 1041722 | D8: 1128798.5 | E8: =D8/B8 -> 0.52005891 | F8: 17241 | G8: =B8/11314544 -> 0.19183456
A9: West | B9: 2055677.9 | C9: 977627.48 | D9: 1078050.4 | E9: =D9/B9 -> 0.52442574 | F9: 15880 | G9: =B9/11314544 -> 0.18168455
A10: TOTAL | B10: =SUM(B5:B9) -> 11314544 | C10: =SUM(C5:C9) -> 5382262.4 | D10: =SUM(D5:D9) -> 5932281.4 | E10: =D10/B10 -> 0.52430584 | F10: =SUM(F5:F9) -> 83685 | G10: 100.0%
A12: KEY FINDINGS
A13: Finding 1: North region leads in total revenue, contributing ~22% of company-wide sales.
A14: Finding 2: South region has the highest GP margin at ~43%, indicating strong pricing power.
A15: Finding 3: Central region is the lowest performer — recommend targeted promotional campaigns.
A16: Recommendation: Reallocate 10-15% of Central's marketing budget to scale North & South initiatives.

Sheet Category Analysis
A1: PRODUCT CATEGORY PERFORMANCE
A4: Category | B4: Total Revenue | C4: Total COGS | D4: Gross Profit | E4: GP Margin % | F4: Total Units | G4: Avg Unit Price
A5: Groceries | B5: 2463240 | C5: 1196021.5 | D5: 1267218.6 | E5: =D5/B5 -> 0.51445192 | F5: 16997 | G5: 143.5
A6: Apparel | B6: 2392165.7 | C6: 1137904.9 | D6: 1254260.8 | E6: =D6/B6 -> 0.52432019 | F6: 16550 | G6: 141.9
A7: Furniture | B7: 2295371 | C7: 1054137.9 | D7: 1241233.1 | E7: =D7/B7 -> 0.54075488 | F7: 16588 | G7: 138.52
A8: Electronics | B8: 2143624.1 | C8: 1034609.9 | D8: 1109014.2 | E8: =D8/B8 -> 0.51735481 | F8: 16599 | G8: 130.37
A9: Sports | B9: 2020143 | C9: 959588.22 | D9: 1060554.8 | E9: =D9/B9 -> 0.52498995 | F9: 16951 | G9: 118.58
A10: TOTAL | B10: =SUM(B5:B9) -> 11314544 | C10: =SUM(C5:C9) -> 5382262.4 | D10: =SUM(D5:D9) -> 5932281.4 | E10: =D10/B10 -> 0.52430584 | F10: =SUM(F5:F9) -> 83685 | G10: =AVERAGE(G5:G9) -> 134.574
